made/__init__.py
made/agent/__init__.py
made/agent/entity/__init__.py
made/agent/entity/agent_response.py
made/agent/repository/__init__.py
made/agent/repository/agent_repository.py
made/agent/repository/agent_repository_impl.py
made/agent/service/__init__.py
made/agent/service/agent_service.py
made/agent/service/agent_service_impl.py
made/chat_chain/__init__.py
made/chat_chain/repository/__init__.py
made/chat_chain/repository/chat_chain_repository.py
made/chat_chain/repository/chat_chain_repository_impl.py
made/chat_chain/service/__init__.py
made/chat_chain/service/chat_chain_service.py
made/chat_chain/service/chat_chain_service_impl.py
made/chat_env/__init__.py
made/chat_env/entity/__init__.py
made/chat_env/entity/env_config.py
made/chat_env/entity/env_states.py
made/chat_env/repository/__init__.py
made/chat_env/repository/chat_env_repository.py
made/chat_env/repository/chat_env_repository_impl.py
made/engine/__init__.py
made/engine/entity/__init__.py
made/engine/entity/ollama_config.py
made/engine/repository/__init__.py
made/engine/repository/base_engine_repository.py
made/engine/repository/huggingface/__init__.py
made/engine/repository/huggingface/huggingface_engine_repository_impl.py
made/engine/repository/ollama/__init__.py
made/engine/repository/ollama/ollama_engine_repository_impl.py
made/engine/service/__init__.py
made/engine/service/base_engine_service.py
made/engine/service/ollama/__init__.py
made/engine/service/ollama/ollama_engine_service_impl.py
made/messages/__init__.py
made/messages/entity/__init__.py
made/messages/entity/base_message.py
made/messages/entity/chat_message/__init__.py
made/messages/entity/chat_message/assistant_message.py
made/messages/entity/chat_message/base_chat_message.py
made/messages/entity/chat_message/user_message.py
made/messages/entity/system_message/__init__.py
made/messages/entity/system_message/assistant_system_message.py
made/messages/entity/system_message/base_system_message.py
llm_made-0.0.14.dist-info/LICENSE
llm_made-0.0.14.dist-info/METADATA
llm_made-0.0.14.dist-info/WHEEL
llm_made-0.0.14.dist-info/top_level.txt
llm_made-0.0.14.dist-info/RECORD
