Metadata-Version: 2.1
Name: llm-made
Version: 0.0.14
Summary: multi-agent development
Home-page: https://github.com/onebottlekick/MADE
Author: onebottlekick
Author-email: gksqudcks97@gmail.com
License: Apache-2.0
Platform: UNKNOWN
Classifier: Programming Language :: Python :: 3
Classifier: License :: OSI Approved :: Apache Software License
Classifier: Operating System :: OS Independent
Requires-Python: >=3.9
License-File: LICENSE
Requires-Dist: openai==1.45.1
Requires-Dist: tenacity==9.0.0
Requires-Dist: docker==7.1.0
Requires-Dist: chromadb==0.5.15
